django_dump_load_utf8/__init__.py
django_dump_load_utf8/admin.py
django_dump_load_utf8/apps.py
django_dump_load_utf8/models.py
django_dump_load_utf8/tests.py
django_dump_load_utf8/views.py
django_dump_load_utf8/management/__init__.py
django_dump_load_utf8/management/commands/__init__.py
django_dump_load_utf8/management/commands/dumpdatautf8.py
django_dump_load_utf8/management/commands/loaddatautf8.py
django_dump_load_utf8/migrations/__init__.py
django_dump_load_utf8-0.0.4.dist-info/LICENSE
django_dump_load_utf8-0.0.4.dist-info/METADATA
django_dump_load_utf8-0.0.4.dist-info/WHEEL
django_dump_load_utf8-0.0.4.dist-info/top_level.txt
django_dump_load_utf8-0.0.4.dist-info/RECORD
