Metadata-Version: 2.1
Name: django-dump-load-utf8
Version: 0.0.4
Summary: Django command dumpdatautf8 and loaddatautf8
Home-page: https://github.com/panhaoyu/django-dump-load-utf8
Author: panhaoyu
Author-email: panhaoyu.china@outlook.com
License: UNKNOWN
Project-URL: Bug Tracker, https://github.com/panhaoyu/django-dump-load-utf8/issues
Platform: UNKNOWN
Classifier: Programming Language :: Python :: 3
Classifier: License :: OSI Approved :: MIT License
Classifier: Operating System :: OS Independent
Requires-Python: >=3.8
License-File: LICENSE
